selocity/__init__.py
selocity/resilient_cached_elements.py
selocity-0.3.1.dist-info/LICENCE.txt
selocity-0.3.1.dist-info/METADATA
selocity-0.3.1.dist-info/WHEEL
selocity-0.3.1.dist-info/RECORD
