Metadata-Version: 2.3
Name: selocity
Version: 0.3.1
Summary: Selocity is a Python library that enhances Selenium's reliability.
License: MIT
Author: jsa34
Author-email: jsa34@cam.ac.uk
Requires-Python: >=3.10
Classifier: License :: OSI Approved :: MIT License
Classifier: Programming Language :: Python :: 3
Classifier: Programming Language :: Python :: 3.10
Classifier: Programming Language :: Python :: 3.11
Classifier: Programming Language :: Python :: 3.12
Classifier: Programming Language :: Python :: 3.13
Requires-Dist: selenium (>=4)
